nyaruko/command/ascii.py
nyaruko/command/bot.py
nyaruko/command/list.py
nyaruko/command/sync.py
nyaruko/config.py
nyaruko/data/ascii-art-big.txt
nyaruko/data/ascii-art.txt
nyaruko/main.py
nyaruko-0.1.0.dist-info/LICENSE
nyaruko-0.1.0.dist-info/METADATA
nyaruko-0.1.0.dist-info/WHEEL
nyaruko-0.1.0.dist-info/RECORD
