Metadata-Version: 2.1
Name: nyaruko
Version: 0.1.0
Summary: This repository is for someone to accomplish something.
License: GPL-3.0 license
Author: niracler
Author-email: i@niracler.com
Requires-Python: >=3.11,<4.0
Classifier: License :: Other/Proprietary License
Classifier: Programming Language :: Python :: 3
Classifier: Programming Language :: Python :: 3.11
Classifier: Programming Language :: Python :: 3.12
Requires-Dist: click (>=8.1.7,<9.0.0)
Requires-Dist: python-telegram-bot[socks] (>=20.7,<21.0)
